{
  "generatedAt": "2026-05-10T21:31:25+05:30",
  "editionDate": "2026-05-10",
  "region": "India",
  "note": "Generated from public RSS feeds; verify source links before editorial use.",
  "fetchStatus": {
    "status": "complete",
    "sourcesConfigured": 6,
    "sourcesSucceeded": 5,
    "sourcesFailed": 1,
    "fetched": 400,
    "accepted": 24,
    "skipped": 242,
    "duplicates": 0,
    "errors": 1
  },
  "sourceStatus": [
    {
      "sourceId": "indian-express",
      "source": "The Indian Express",
      "status": "ok",
      "feedUrl": "https://indianexpress.com/section/india/feed/",
      "sourceType": "newspaper",
      "section": "India",
      "countryScope": "India",
      "isFreeToRead": true,
      "policyNotes": "Indian newspaper; official public India section RSS feed.",
      "fetched": 200,
      "accepted": 19,
      "skipped": 181,
      "duplicates": 0,
      "error": null
    },
    {
      "sourceId": "times-of-india",
      "source": "The Times of India",
      "status": "ok",
      "feedUrl": "https://timesofindia.indiatimes.com/rssfeeds/-2128936835.cms",
      "sourceType": "newspaper",
      "section": "India",
      "countryScope": "India",
      "isFreeToRead": true,
      "policyNotes": "Indian newspaper; public India RSS feed.",
      "fetched": 20,
      "accepted": 0,
      "skipped": 20,
      "duplicates": 0,
      "error": null
    },
    {
      "sourceId": "ndtv",
      "source": "NDTV",
      "status": "ok",
      "feedUrl": "https://feeds.feedburner.com/ndtvnews-india-news",
      "sourceType": "digital_news_publisher",
      "section": "India",
      "countryScope": "India",
      "isFreeToRead": true,
      "policyNotes": "Free public India news feed; included as online source data but not a strict newspaper source.",
      "fetched": 20,
      "accepted": 20,
      "skipped": 0,
      "duplicates": 0,
      "error": null
    },
    {
      "sourceId": "hindustan-times",
      "source": "Hindustan Times",
      "status": "ok",
      "feedUrl": "https://www.hindustantimes.com/feeds/rss/india-news/rssfeed.xml",
      "sourceType": "newspaper",
      "section": "India",
      "countryScope": "India",
      "isFreeToRead": true,
      "policyNotes": "Indian newspaper; official public India news RSS feed.",
      "fetched": 100,
      "accepted": 59,
      "skipped": 41,
      "duplicates": 0,
      "error": null
    },
    {
      "sourceId": "the-hindu",
      "source": "The Hindu",
      "status": "ok",
      "feedUrl": "https://www.thehindu.com/news/national/feeder/default.rss",
      "sourceType": "newspaper",
      "section": "National",
      "countryScope": "India",
      "isFreeToRead": true,
      "policyNotes": "Indian newspaper; official public national news RSS feed.",
      "fetched": 60,
      "accepted": 60,
      "skipped": 0,
      "duplicates": 0,
      "error": null
    },
    {
      "sourceId": "business-standard",
      "source": "Business Standard",
      "status": "error",
      "feedUrl": "https://www.business-standard.com/rss/latest.rss",
      "sourceType": "newspaper",
      "section": "Latest",
      "countryScope": "India",
      "isFreeToRead": true,
      "policyNotes": "Indian business newspaper; current public feed is generic latest news and may fail or include non-India items.",
      "fetched": 0,
      "accepted": 0,
      "skipped": 0,
      "duplicates": 0,
      "error": "HTTP Error 403: Forbidden"
    }
  ],
  "sources": [
    {
      "id": "indian-express",
      "name": "The Indian Express",
      "url": "https://indianexpress.com/section/india/",
      "feedUrl": "https://indianexpress.com/section/india/feed/",
      "sourceType": "newspaper",
      "section": "India",
      "countryScope": "India",
      "isFreeToRead": true,
      "policyNotes": "Indian newspaper; official public India section RSS feed."
    },
    {
      "id": "times-of-india",
      "name": "The Times of India",
      "url": "https://timesofindia.indiatimes.com/india",
      "feedUrl": "https://timesofindia.indiatimes.com/rssfeeds/-2128936835.cms",
      "sourceType": "newspaper",
      "section": "India",
      "countryScope": "India",
      "isFreeToRead": true,
      "policyNotes": "Indian newspaper; public India RSS feed."
    },
    {
      "id": "ndtv",
      "name": "NDTV",
      "url": "https://www.ndtv.com/india-news",
      "feedUrl": "https://feeds.feedburner.com/ndtvnews-india-news",
      "sourceType": "digital_news_publisher",
      "section": "India",
      "countryScope": "India",
      "isFreeToRead": true,
      "policyNotes": "Free public India news feed; included as online source data but not a strict newspaper source."
    },
    {
      "id": "hindustan-times",
      "name": "Hindustan Times",
      "url": "https://www.hindustantimes.com/india-news",
      "feedUrl": "https://www.hindustantimes.com/feeds/rss/india-news/rssfeed.xml",
      "sourceType": "newspaper",
      "section": "India",
      "countryScope": "India",
      "isFreeToRead": true,
      "policyNotes": "Indian newspaper; official public India news RSS feed."
    },
    {
      "id": "the-hindu",
      "name": "The Hindu",
      "url": "https://www.thehindu.com/news/national/",
      "feedUrl": "https://www.thehindu.com/news/national/feeder/default.rss",
      "sourceType": "newspaper",
      "section": "National",
      "countryScope": "India",
      "isFreeToRead": true,
      "policyNotes": "Indian newspaper; official public national news RSS feed."
    },
    {
      "id": "business-standard",
      "name": "Business Standard",
      "url": "https://www.business-standard.com/india-news",
      "feedUrl": "https://www.business-standard.com/rss/latest.rss",
      "sourceType": "newspaper",
      "section": "Latest",
      "countryScope": "India",
      "isFreeToRead": true,
      "policyNotes": "Indian business newspaper; current public feed is generic latest news and may fail or include non-India items."
    }
  ],
  "headlines": [
    {
      "id": "indian-express-himanta-biswa-sarma-elected-party-leader-for-second-time-to-be-sworn-in-as-",
      "sourceId": "indian-express",
      "source": "The Indian Express",
      "title": "Himanta Biswa Sarma elected party leader for second time, to be sworn-in as Assam CM on May 12",
      "category": "India",
      "priority": "Lead",
      "url": "https://indianexpress.com/article/india/himanta-biswa-sarma-elected-party-leader-assam-cm-10682783",
      "publishedAt": "2026-05-10T21:28:38+05:30"
    },
    {
      "id": "the-hindu-g-sudhakaran-visits-social-and-religious-leaders",
      "sourceId": "the-hindu",
      "source": "The Hindu",
      "title": "G. Sudhakaran visits social and religious leaders",
      "category": "India",
      "priority": "Lead",
      "url": "https://www.thehindu.com/news/national/kerala/g-sudhakaran-visits-social-and-religious-leaders/article70962953.ece",
      "publishedAt": "2026-05-10T21:24:06+05:30"
    },
    {
      "id": "the-hindu-telangana-bjp-chief-s-special-memento-for-modi",
      "sourceId": "the-hindu",
      "source": "The Hindu",
      "title": "Telangana BJP chief’s special memento for Modi",
      "category": "India",
      "priority": "Lead",
      "url": "https://www.thehindu.com/news/national/telangana/telangana-bjp-chiefs-special-memento-for-modi/article70963087.ece",
      "publishedAt": "2026-05-10T21:23:29+05:30"
    },
    {
      "id": "the-hindu-modi-visits-naidu-pawan-in-hyderabad",
      "sourceId": "the-hindu",
      "source": "The Hindu",
      "title": "Modi visits Naidu, Pawan in Hyderabad",
      "category": "India",
      "priority": "Lead",
      "url": "https://www.thehindu.com/news/national/andhra-pradesh/modi-visits-naidu-pawan-in-hyderabad/article70962984.ece",
      "publishedAt": "2026-05-10T21:21:59+05:30"
    },
    {
      "id": "the-hindu-uttar-pradesh-cabinet-expanded-with-six-new-ministers",
      "sourceId": "the-hindu",
      "source": "The Hindu",
      "title": "Uttar Pradesh Cabinet expanded with six new Ministers",
      "category": "India",
      "priority": "Lead",
      "url": "https://www.thehindu.com/news/national/uttar-pradesh/uttar-pradesh-government-expansion-yogi-adityanath-ministry/article70962176.ece",
      "publishedAt": "2026-05-10T21:21:33+05:30"
    },
    {
      "id": "the-hindu-brs-leader-praveen-kumar-demands-sit-probe-with-women-police-officers-into-pocso",
      "sourceId": "the-hindu",
      "source": "The Hindu",
      "title": "BRS leader Praveen Kumar demands SIT probe with women police officers into POCSO case against Bandi Sanjay’s son",
      "category": "India",
      "priority": "High",
      "url": "https://www.thehindu.com/news/national/telangana/brs-leader-praveen-kumar-demands-sit-probe-with-women-police-officers-into-pocso-case-against-bandi-sanjays-son/article70962996.ece",
      "publishedAt": "2026-05-10T21:19:47+05:30"
    },
    {
      "id": "the-hindu-tamil-nadu-government-formation-updates-tn-assembly-to-convene-first-session-spe",
      "sourceId": "the-hindu",
      "source": "The Hindu",
      "title": "Tamil Nadu government formation updates: TN Assembly to convene first session; Speaker election on May 12",
      "category": "India",
      "priority": "High",
      "url": "https://www.thehindu.com/elections/tamil-nadu-assembly/tamil-nadu-government-formation-tvk-swearing-in-vijay-oath-ceremony-new-chief-minister-live-updates-may-10-2026/article70960233.ece",
      "publishedAt": "2026-05-10T21:18:57+05:30"
    },
    {
      "id": "indian-express-refrain-from-foreign-travel-buying-gold-for-a-year-pm-modi-s-appeal-amid-we",
      "sourceId": "indian-express",
      "source": "The Indian Express",
      "title": "Refrain from foreign travel, buying gold for a year: PM Modi’s appeal amid West Asia crisis",
      "category": "India",
      "priority": "High",
      "url": "https://indianexpress.com/article/india/pm-modi-hyderabad-speech-west-asia-crisis-petrol-diesel-gold-reduction-10682817",
      "publishedAt": "2026-05-10T21:18:50+05:30"
    },
    {
      "id": "the-hindu-kochi-lakshadweep-seaplane-trial-flight-rescheduled-to-may-12",
      "sourceId": "the-hindu",
      "source": "The Hindu",
      "title": "Kochi-Lakshadweep seaplane trial flight rescheduled to May 12",
      "category": "India",
      "priority": "High",
      "url": "https://www.thehindu.com/news/national/kerala/kochi-lakshadweep-seaplane-trial-flight-rescheduled-to-may-12/article70962824.ece",
      "publishedAt": "2026-05-10T21:17:37+05:30"
    },
    {
      "id": "the-hindu-bandi-urges-bjp-workers-to-not-believe-allegations",
      "sourceId": "the-hindu",
      "source": "The Hindu",
      "title": "Bandi urges BJP workers to not believe allegations",
      "category": "India",
      "priority": "High",
      "url": "https://www.thehindu.com/news/national/telangana/bandi-urges-bjp-workers-to-not-believe-allegations/article70962998.ece",
      "publishedAt": "2026-05-10T21:16:38+05:30"
    },
    {
      "id": "the-hindu-dissent-brews-in-cpi-m-as-two-dozen-members-quit-in-palakkad",
      "sourceId": "the-hindu",
      "source": "The Hindu",
      "title": "Dissent brews in CPI(M) as two dozen members quit in Palakkad",
      "category": "India",
      "priority": "High",
      "url": "https://www.thehindu.com/news/national/kerala/dissent-brews-in-cpim-as-two-dozen-members-quit-in-palakkad/article70962895.ece",
      "publishedAt": "2026-05-10T21:13:54+05:30"
    },
    {
      "id": "the-hindu-81st-anniversary-of-soviet-union-s-victory-in-world-war-ii-celebrated",
      "sourceId": "the-hindu",
      "source": "The Hindu",
      "title": "81st anniversary of Soviet Union’s victory in World War II celebrated",
      "category": "India",
      "priority": "High",
      "url": "https://www.thehindu.com/news/national/kerala/81st-anniversary-of-soviet-unions-victory-in-world-war-ii-celebrated-in-thiruvananthapuram/article70962837.ece",
      "publishedAt": "2026-05-10T21:13:48+05:30"
    },
    {
      "id": "the-hindu-karuppaiah-sworn-in-as-pro-tem-speaker",
      "sourceId": "the-hindu",
      "source": "The Hindu",
      "title": "Karuppaiah sworn-in as Pro-tem Speaker",
      "category": "India",
      "priority": "Medium",
      "url": "https://www.thehindu.com/news/national/tamil-nadu/karuppaiah-sworn-in-as-pro-tem-speaker/article70962378.ece",
      "publishedAt": "2026-05-10T21:12:57+05:30"
    },
    {
      "id": "the-hindu-bjp-poised-for-power-in-telangana-as-people-show-bengal-like-enthusiasm-modi",
      "sourceId": "the-hindu",
      "source": "The Hindu",
      "title": "BJP poised for power in Telangana as people show Bengal-like enthusiasm: Modi",
      "category": "India",
      "priority": "Medium",
      "url": "https://www.thehindu.com/news/national/telangana/bjp-poised-for-power-in-telangana-as-people-show-bengal-like-enthusiasm-modi/article70962954.ece",
      "publishedAt": "2026-05-10T21:12:14+05:30"
    },
    {
      "id": "the-hindu-deputy-cm-bhatti-submits-plea-to-pm-modi-on-bc-census",
      "sourceId": "the-hindu",
      "source": "The Hindu",
      "title": "Deputy CM Bhatti submits plea to PM Modi on BC Census",
      "category": "India",
      "priority": "Medium",
      "url": "https://www.thehindu.com/news/national/telangana/deputy-cm-bhatti-submits-plea-to-pm-modi-on-bc-census/article70963013.ece",
      "publishedAt": "2026-05-10T21:08:03+05:30"
    },
    {
      "id": "the-hindu-manhunt-on-for-history-sheeter-in-thiruvananthapuram-sexual-abuse-case",
      "sourceId": "the-hindu",
      "source": "The Hindu",
      "title": "Manhunt on for history-sheeter in Thiruvananthapuram sexual abuse case",
      "category": "India",
      "priority": "Medium",
      "url": "https://www.thehindu.com/news/national/kerala/manhunt-on-for-history-sheeter-in-thiruvananthapuram-sexual-abuse-case/article70962866.ece",
      "publishedAt": "2026-05-10T21:07:52+05:30"
    },
    {
      "id": "ndtv-wfh-no-foreign-weddings-pm-modi-s-strategy-to-combat-rising-prices",
      "sourceId": "ndtv",
      "source": "NDTV",
      "title": "WFH, No Foreign Weddings: PM Modi's Strategy To Combat Rising Prices",
      "category": "India",
      "priority": "Medium",
      "url": "https://www.ndtv.com/india-news/wfh-no-foreign-weddings-pm-modis-strategy-to-combat-rising-prices-11475683",
      "publishedAt": "2026-05-10T21:07:40+05:30"
    },
    {
      "id": "the-hindu-six-injured-in-bus-mini-bus-collision-on-erattupetta-wagamon-route",
      "sourceId": "the-hindu",
      "source": "The Hindu",
      "title": "Six injured in bus–mini bus collision on Erattupetta–Wagamon route",
      "category": "India",
      "priority": "Medium",
      "url": "https://www.thehindu.com/news/national/kerala/six-injured-in-busmini-bus-collision-on-erattupettavagamon-route/article70962242.ece",
      "publishedAt": "2026-05-10T21:04:30+05:30"
    },
    {
      "id": "ndtv-vande-mataram-vs-tamil-anthem-vijay-s-oath-sparks-first-dmk-tvk-battle",
      "sourceId": "ndtv",
      "source": "NDTV",
      "title": "Vande Mataram Vs Tamil Anthem: Vijay's Oath Sparks First DMK-TVK Battle",
      "category": "India",
      "priority": "Medium",
      "url": "https://www.ndtv.com/india-news/vande-mataram-vs-tamil-anthem-vijays-oath-sparks-first-dmk-tvk-battle-11475525",
      "publishedAt": "2026-05-10T21:02:20+05:30"
    },
    {
      "id": "the-hindu-one-more-held-in-alleged-organ-donation-fraud-in-kerala",
      "sourceId": "the-hindu",
      "source": "The Hindu",
      "title": "One more held in alleged organ donation fraud in Kerala",
      "category": "India",
      "priority": "Medium",
      "url": "https://www.thehindu.com/news/national/kerala/one-more-held-from-up-in-alleged-organ-donation-fraud-in-kerala/article70962886.ece",
      "publishedAt": "2026-05-10T21:01:15+05:30"
    },
    {
      "id": "the-hindu-in-tamil-nadu-assembly-it-s-vijay-versus-udhayanidhi",
      "sourceId": "the-hindu",
      "source": "The Hindu",
      "title": "In Tamil Nadu Assembly, it’s Vijay versus Udhayanidhi",
      "category": "India",
      "priority": "Medium",
      "url": "https://www.thehindu.com/news/national/tamil-nadu/udhayanidhi-stalin-dmk-leader-of-opposition/article70962587.ece",
      "publishedAt": "2026-05-10T20:57:44+05:30"
    },
    {
      "id": "the-hindu-pm-modi-inaugurates-sindhu-hospital-in-hyderabad-lauds-focus-on-technology-and-i",
      "sourceId": "the-hindu",
      "source": "The Hindu",
      "title": "PM Modi inaugurates Sindhu Hospital in Hyderabad, lauds focus on technology and innovation",
      "category": "India",
      "priority": "Medium",
      "url": "https://www.thehindu.com/news/cities/Hyderabad/pm-modi-inaugurates-sindhu-hospital-in-hyderabad-lauds-focus-on-technology-and-innovation/article70962897.ece",
      "publishedAt": "2026-05-10T20:57:43+05:30"
    },
    {
      "id": "ndtv-grabbed-its-neck-13-year-old-boy-s-daring-face-off-with-leopard",
      "sourceId": "ndtv",
      "source": "NDTV",
      "title": "'Grabbed Its Neck': 13-Year-Old Boy's Daring Face-Off With Leopard",
      "category": "India",
      "priority": "Medium",
      "url": "https://www.ndtv.com/india-news/grabbed-its-neck-13-year-old-boys-daring-face-off-with-leopard-11475695",
      "publishedAt": "2026-05-10T20:55:43+05:30"
    },
    {
      "id": "the-hindu-1-600-tonnes-of-dry-fodder-donated-to-ttd-s-cow-shelter",
      "sourceId": "the-hindu",
      "source": "The Hindu",
      "title": "1,600 tonnes of dry fodder donated to TTD’s cow shelter",
      "category": "India",
      "priority": "Medium",
      "url": "https://www.thehindu.com/news/national/andhra-pradesh/1600-tonnes-of-dry-fodder-donated-to-ttds-cow-shelter/article70962617.ece",
      "publishedAt": "2026-05-10T20:50:47+05:30"
    }
  ]
}
